{
  "performance": [
    {
      "symbol": "BTC",
      "total_trades": 476,
      "acuracia_5s": 37.0,
      "acuracia_15s": 44.0,
      "acuracia_30s": 60.0,
      "acuracia_60s": 52.0,
      "acuracia_300s": 61.0,
      "acuracia_900s": 70.6
    },
    {
      "symbol": "ETH",
      "total_trades": 476,
      "acuracia_5s": 39.0,
      "acuracia_15s": 52.0,
      "acuracia_30s": 68.0,
      "acuracia_60s": 53.0,
      "acuracia_300s": 44.1,
      "acuracia_900s": 64.7
    }
  ],
  "total_trades": 6118,
  "acuracia_geral": 54.1,
  "profit_factor": 1.18
}